{
  "project_info": {
    "project_number": "272709421121",
    "project_id": "project-recipe-1a94e",
    "storage_bucket": "project-recipe-1a94e.appspot.com"
  },
  "client": [
    {
      "client_info": {
        "mobilesdk_app_id": "1:272709421121:android:04003b025f9eb4d7951ec0",
        "android_client_info": {
          "package_name": "app.recipe.ai"
        }
      },
      "oauth_client": [
        {
          "client_id": "272709421121-q03vqaa6vii2rutlbp5mo6gsb1oj6vje.apps.googleusercontent.com",
          "client_type": 3
        }
      ],
      "api_key": [
        {
          "current_key": "AIzaSyDFVLAMpttIrg1TkeASNJXBJs4cU3muRPM"
        }
      ],
      "services": {
        "appinvite_service": {
          "other_platform_oauth_client": [
            {
              "client_id": "272709421121-q03vqaa6vii2rutlbp5mo6gsb1oj6vje.apps.googleusercontent.com",
              "client_type": 3
            },
            {
              "client_id": "272709421121-46koccp88s0ocgbj9db2af5p5vbtphbn.apps.googleusercontent.com",
              "client_type": 2,
              "ios_info": {
                "bundle_id": "com.example.recipe"
              }
            }
          ]
        }
      }
    },
    {
      "client_info": {
        "mobilesdk_app_id": "1:272709421121:android:9fc32cb6fb8dd951951ec0",
        "android_client_info": {
          "package_name": "com.example.recipe"
        }
      },
      "oauth_client": [
        {
          "client_id": "272709421121-g4mrb1k14ndm0jiu4jsmnkaab4loia1f.apps.googleusercontent.com",
          "client_type": 1,
          "android_info": {
            "package_name": "com.example.recipe",
            "certificate_hash": "f3d94e7b846fbd450c4cc60b7edce63a75c1406b"
          }
        },
        {
          "client_id": "272709421121-q03vqaa6vii2rutlbp5mo6gsb1oj6vje.apps.googleusercontent.com",
          "client_type": 3
        }
      ],
      "api_key": [
        {
          "current_key": "AIzaSyDFVLAMpttIrg1TkeASNJXBJs4cU3muRPM"
        }
      ],
      "services": {
        "appinvite_service": {
          "other_platform_oauth_client": [
            {
              "client_id": "272709421121-q03vqaa6vii2rutlbp5mo6gsb1oj6vje.apps.googleusercontent.com",
              "client_type": 3
            },
            {
              "client_id": "272709421121-46koccp88s0ocgbj9db2af5p5vbtphbn.apps.googleusercontent.com",
              "client_type": 2,
              "ios_info": {
                "bundle_id": "com.example.recipe"
              }
            }
          ]
        }
      }
    }
  ],
  "configuration_version": "1"
}